Metadata-Version: 1.2
Name: pypledge
Version: 0.3.1
Summary: Binding for the OpenBSD pledge(2) system call
Home-page: https://gitlab.com/i80and/pypledge
Maintainer: Andrew Aldridge
Maintainer-email: i80and@foxquill.com
License: MIT
Platform: UNKNOWN
Classifier: Development Status :: 4 - Beta
Classifier: Intended Audience :: Developers
Classifier: License :: OSI Approved :: MIT License
Classifier: Operating System :: POSIX :: BSD :: OpenBSD
Classifier: Programming Language :: Python :: 3 :: Only
Classifier: Topic :: Security
Classifier: Topic :: Software Development :: Libraries :: Python Modules
